t2f/__init__.py
t2f/patched_asm.py
t2f/stdlib.py
t2f/t2f.py
t2f/utils.py
t2f-0.1.8.dist-info/METADATA
t2f-0.1.8.dist-info/WHEEL
t2f-0.1.8.dist-info/entry_points.txt
t2f-0.1.8.dist-info/RECORD
