Metadata-Version: 2.1
Name: t2f
Version: 0.1.8
Summary: TVM Assembly to Fift Assembly Translator
Author: Andrew Gutarev
Author-email: gutarev01@gmail.com
Requires-Python: >=3.8,<4.0
Classifier: Programming Language :: Python :: 3
Classifier: Programming Language :: Python :: 3.8
Classifier: Programming Language :: Python :: 3.9
Classifier: Programming Language :: Python :: 3.10
Classifier: Programming Language :: Python :: 3.11
